mykrobe/__init__.py
mykrobe/base.py
mykrobe/mykrobe_predictor.py
mykrobe/utils.py
mykrobe/version.py
mykrobe/cmds/__init__.py
mykrobe/cmds/amr.py
mykrobe/data/panels/staph-amr-bradley_2015-feb-17-2017.fasta.gz
mykrobe/data/panels/staph-species-160227.fasta.gz
mykrobe/data/panels/tb-bradley-probe-set-feb-09-2017.fasta.gz
mykrobe/data/panels/tb-species-160330.fasta.gz
mykrobe/data/panels/tb-species-170421.fasta.gz
mykrobe/data/panels/tb-walker-probe-set-feb-09-2017.fasta.gz
mykrobe/data/phylo/mtbc_hierarchy.json
mykrobe/data/predict/taxon_coverage_threshold.json
mykrobe/data/predict/gn/variant_to_resistance_drug.json
mykrobe/data/predict/staph/variant_to_resistance_drug.json
mykrobe/data/predict/tb/variant_to_resistance_drug.json
mykrobe/metagenomics/__init__.py
mykrobe/metagenomics/models.py
mykrobe/metagenomics/phylo.py
mykrobe/predict/__init__.py
mykrobe/predict/amr.py
mykrobe/predict/models.py
mykrobe-0.5.6.dist-info/DESCRIPTION.rst
mykrobe-0.5.6.dist-info/METADATA
mykrobe-0.5.6.dist-info/RECORD
mykrobe-0.5.6.dist-info/WHEEL
mykrobe-0.5.6.dist-info/entry_points.txt
mykrobe-0.5.6.dist-info/metadata.json
mykrobe-0.5.6.dist-info/top_level.txt
